iadpython/__init__.py
iadpython/ad.py
iadpython/combine.py
iadpython/constants.py
iadpython/fresnel.py
iadpython/grid.py
iadpython/iad.py
iadpython/iadc.py
iadpython/nist.py
iadpython/quadrature.py
iadpython/redistribution.py
iadpython/rxt.py
iadpython/sphere.py
iadpython/start.py
iadpython-0.5.3.dist-info/LICENSE.txt
iadpython-0.5.3.dist-info/METADATA
iadpython-0.5.3.dist-info/WHEEL
iadpython-0.5.3.dist-info/top_level.txt
iadpython-0.5.3.dist-info/zip-safe
iadpython-0.5.3.dist-info/RECORD
