Metadata-Version: 2.1
Name: iadpython
Version: 0.5.3
Summary: 'Forward and inverse radiative transport using adding-doubling'
Home-page: https://github.com/scottprahl/iadpython.git
Author: Scott Prahl
Author-email: scott.prahl@oit.edu
License: MIT
Keywords: absorption,scattering,reflection,transmission,optical properties,radiative transport,optical properties,scattering coefficient,scattering anisotropy
Classifier: Development Status :: 3 - Alpha
Classifier: License :: OSI Approved :: MIT License
Classifier: Intended Audience :: Science/Research
Classifier: Programming Language :: Python
Classifier: Topic :: Scientific/Engineering :: Physics
Classifier: Programming Language :: Python :: 3
Classifier: Programming Language :: Python :: 3.8
Classifier: Programming Language :: Python :: 3.9
Classifier: Programming Language :: Python :: 3.10
Classifier: Programming Language :: Python :: 3.11
Requires-Python: >=3.7
License-File: LICENSE.txt
Requires-Dist: numpy
